COPYING
MANIFEST.in
README
setup.py
pylaf.egg-info/PKG-INFO
pylaf.egg-info/SOURCES.txt
pylaf.egg-info/dependency_links.txt
pylaf.egg-info/top_level.txt
src/pylaf/__init__.py
src/pylaf/core.py
src/pylaf/ez.py
src/pylaf/gui.py
src/pylaf/gui_old.py
src/pylaf/kitchen.py
src/pylaf/mpl.py
src/pylaf/thread.py
src/pylaf/vtkext.py
src/pylaf/widgets.py
src/pylaf/recipes/__init__.py
src/pylaf/recipes/fdtd.py
src/pylaf/utils/__init__.py
src/pylaf/utils/functions.py
src/pylaf/utils/core/__init__.py
src/pylaf/utils/core/observer.py
src/pylaf/utils/core/singleton.py
src/pylaf/utils/core/weakvaluelist.py
src/pylaf/utils/gui/__init__.py
src/pylaf/utils/gui/gui.py
src/pylaf/utils/gui/tkwidgets.py
src/pylaf/utils/mpl/__init__.py
src/pylaf/utils/mpl/mpl.py
src/pylaf/utils/mpl/tkwidgets.py