Metadata-Version: 1.0
Name: pylaf
Version: 0.3.2
Summary: Python Laboratory Application Framework
Home-page: http://pylaf.sourceforge.jp
Author: Hidehisa Shiomi
Author-email: pylaf@users.sourceforge.jp
License: BSD
Keywords: framework
Platform: UNKNOWN
Classifier: Development Status :: 3 - Alpha
Classifier: License :: OSI Approved :: BSD License
Classifier: Programming Language :: Python
Classifier: Topic :: Software Development
